scheduler/__init__.py
scheduler/whatsapp.py
whatsapptimer-1.0.0.dist-info/METADATA
whatsapptimer-1.0.0.dist-info/WHEEL
whatsapptimer-1.0.0.dist-info/top_level.txt
whatsapptimer-1.0.0.dist-info/RECORD
